schedula/__init__.py
schedula/_version.py
schedula/cli.py
schedula/dispatcher.py
schedula/ext/__init__.py
schedula/ext/autosummary.py
schedula/ext/dispatcher/__init__.py
schedula/ext/dispatcher/documenter.py
schedula/ext/dispatcher/graphviz.py
schedula/utils/__init__.py
schedula/utils/alg.py
schedula/utils/base.py
schedula/utils/blue.py
schedula/utils/cst.py
schedula/utils/dsp.py
schedula/utils/exc.py
schedula/utils/gen.py
schedula/utils/graph.py
schedula/utils/imp.py
schedula/utils/sol.py
schedula/utils/utl.py
schedula/utils/asy/__init__.py
schedula/utils/asy/executors.py
schedula/utils/asy/factory.py
schedula/utils/des/__init__.py
schedula/utils/drw/__init__.py
schedula/utils/drw/nodes.py
schedula/utils/drw/index/css/bootstrap.min.css
schedula/utils/drw/index/css/bootstrap.min.css.map
schedula/utils/drw/index/css/icon.css
schedula/utils/drw/index/css/index.css
schedula/utils/drw/index/js/bootstrap-treeview.min.js
schedula/utils/drw/index/js/bootstrap.min.js
schedula/utils/drw/index/js/bootstrap.min.js.map
schedula/utils/drw/index/js/d3-scale.v3.min.js
schedula/utils/drw/index/js/jquery-3.7.1.min.js
schedula/utils/drw/index/js/jquery.fullscreen.min.js
schedula/utils/drw/index/js/sunburst-chart.min.js
schedula/utils/drw/templates/index.html
schedula/utils/drw/templates/render.html
schedula/utils/drw/viz/viz.js
schedula/utils/form/__init__.py
schedula/utils/form/cli.py
schedula/utils/form/config.py
schedula/utils/form/gapp.py
schedula/utils/form/sample/.babelrc
schedula/utils/form/sample/app.py
schedula/utils/form/sample/package.json
schedula/utils/form/sample/webpack.config.js
schedula/utils/form/sample/src/index/customValidate.js
schedula/utils/form/sample/src/index/editOnChange.js
schedula/utils/form/sample/src/index/index.css
schedula/utils/form/sample/src/index/index.js
schedula/utils/form/sample/src/index/postSubmit.js
schedula/utils/form/sample/src/index/preSubmit.js
schedula/utils/form/sample/src/index/transformErrors.js
schedula-1.5.78.dist-info/licenses/AUTHORS.rst
schedula-1.5.78.dist-info/licenses/LICENSE.txt
schedula-1.5.78.dist-info/METADATA
schedula-1.5.78.dist-info/WHEEL
schedula-1.5.78.dist-info/entry_points.txt
schedula-1.5.78.dist-info/top_level.txt
schedula-1.5.78.dist-info/RECORD
